[["Platform",{"animations":"{\"expanded\":true,\"subfolders\":[]}"}],["Clouds",{"animations":"{\"expanded\":true,\"subfolders\":[]}"}],["clowd",{"animations":"{\"expanded\":true,\"subfolders\":[]}"}],["SandSpriteTL",{"animations":"{\"expanded\":true,\"subfolders\":[]}"}],["SandSpriteML",{"animations":"{\"expanded\":true,\"subfolders\":[]}"}],["SandSpriteBL",{"animations":"{\"expanded\":true,\"subfolders\":[]}"}],["SandSpriteBR",{"animations":"{\"expanded\":true,\"subfolders\":[]}"}],["clowd2",{"animations":"{\"expanded\":true,\"subfolders\":[]}"}],["Player",{"animations":"{\"expanded\":true,\"subfolders\":[]}"}],["AcidSlime",{"animations":"{\"expanded\":true,\"subfolders\":[]}"}],["BossSlime",{"animations":"{\"expanded\":true,\"subfolders\":[]}"}],["EarthSlime",{"animations":"{\"expanded\":true,\"subfolders\":[]}"}],["FireBall",{"animations":"{\"expanded\":true,\"subfolders\":[]}"}],["FireSlime",{"animations":"{\"expanded\":true,\"subfolders\":[]}"}],["FrostSlime",{"animations":"{\"expanded\":true,\"subfolders\":[]}"}],["LavaSlime",{"animations":"{\"expanded\":true,\"subfolders\":[]}"}],["LighteningBolt",{"animations":"{\"expanded\":true,\"subfolders\":[]}"}],["LightningSlime",{"animations":"{\"expanded\":true,\"subfolders\":[]}"}],["PoisonPuddle",{"animations":"{\"expanded\":true,\"subfolders\":[]}"}],["PoisonSlime",{"animations":"{\"expanded\":true,\"subfolders\":[]}"}],["Slime",{"animations":"{\"expanded\":true,\"subfolders\":[]}"}],["stasis",{"animations":"{\"expanded\":true,\"subfolders\":[]}"}],["WaterSlime",{"animations":"{\"expanded\":true,\"subfolders\":[]}"}],["Player2",{"animations":"{\"expanded\":true,\"subfolders\":[]}"}],["CaveSpriteTL",{"animations":"{\"expanded\":true,\"subfolders\":[]}"}],["MovingGround2",{"animations":"{\"expanded\":true,\"subfolders\":[]}"}]]